pygmp/__init__.py
pygmp/log_config.ini
pygmp/_kernel.c
pygmp/_kernel.cpython-310-i386-linux-gnu.so
pygmp/utils.py
pygmp/util.c
pygmp/__main__.py
pygmp/data.py
pygmp/kernel.py
pygmp/daemons/__init__.py
pygmp/daemons/utils.py
pygmp/daemons/interactive.py
pygmp/daemons/simple.py
pygmp/daemons/config.py
py_gmp-0.0.2.dist-info/METADATA
py_gmp-0.0.2.dist-info/LICENSE
py_gmp-0.0.2.dist-info/RECORD
py_gmp-0.0.2.dist-info/top_level.txt
py_gmp-0.0.2.dist-info/WHEEL
