Metadata-Version: 2.1
Name: py-gmp
Version: 0.0.2
Summary: Linux Multicast Routing.
Author-email: Jack Hart <jackhart0508@gmail.com>
Maintainer-email: Jack Hart <jackhart0508@gmail.com>
License: MIT License
Project-URL: Source, https://github.com/jackhart/pygmp
Classifier: Development Status :: 3 - Alpha
Classifier: Operating System :: POSIX :: Linux
Classifier: License :: OSI Approved :: MIT License
Classifier: Topic :: Multimedia :: Video
Classifier: Topic :: System :: Networking
Classifier: Topic :: System :: Operating System Kernels :: Linux
Requires-Python: >=3.8
License-File: LICENSE
Provides-Extra: daemons
Requires-Dist: fastapi ; extra == 'daemons'
Requires-Dist: uvicorn ; extra == 'daemons'
